mispstix2/__init__.py
mispstix2/base.py
mispstix2/canonicalization/Canonicalize.py
mispstix2/canonicalization/NumberToJson.py
mispstix2/canonicalization/__init__.py
mispstix2/confidence/__init__.py
mispstix2/confidence/scales.py
mispstix2/custom.py
mispstix2/datastore/__init__.py
mispstix2/datastore/filesystem.py
mispstix2/datastore/filters.py
mispstix2/datastore/memory.py
mispstix2/datastore/taxii.py
mispstix2/environment.py
mispstix2/equivalence/__init__.py
mispstix2/equivalence/graph/__init__.py
mispstix2/equivalence/object/__init__.py
mispstix2/equivalence/pattern/__init__.py
mispstix2/equivalence/pattern/compare/__init__.py
mispstix2/equivalence/pattern/compare/comparison.py
mispstix2/equivalence/pattern/compare/observation.py
mispstix2/equivalence/pattern/transform/__init__.py
mispstix2/equivalence/pattern/transform/comparison.py
mispstix2/equivalence/pattern/transform/observation.py
mispstix2/equivalence/pattern/transform/specials.py
mispstix2/exceptions.py
mispstix2/hashes.py
mispstix2/markings/__init__.py
mispstix2/markings/granular_markings.py
mispstix2/markings/object_markings.py
mispstix2/markings/utils.py
mispstix2/parsing.py
mispstix2/pattern_visitor.py
mispstix2/patterns.py
mispstix2/properties.py
mispstix2/registration.py
mispstix2/registry.py
mispstix2/serialization.py
mispstix2/test/__init__.py
mispstix2/test/test_hashes.py
mispstix2/test/test_pattern_equivalence.py
mispstix2/test/test_properties.py
mispstix2/test/test_spec_version_detect.py
mispstix2/test/test_utils_type_checks.py
mispstix2/test/test_workbench.py
mispstix2/test/v20/__init__.py
mispstix2/test/v20/conftest.py
mispstix2/test/v20/constants.py
mispstix2/test/v20/pattern_ast_overrides.py
mispstix2/test/v20/stix2_data/attack-pattern/attack-pattern--0a3ead4e-6d47-4ccb-854c-a6a4f9d96b22/20170531213019735010.json
mispstix2/test/v20/stix2_data/attack-pattern/attack-pattern--0f20e3cb-245b-4a61-8a91-2d93f7cb0e9b/20170531213026496201.json
misp_stix2-4.0.0.dist-info/LICENSE
misp_stix2-4.0.0.dist-info/METADATA
misp_stix2-4.0.0.dist-info/WHEEL
misp_stix2-4.0.0.dist-info/RECORD
