Metadata-Version: 2.1
Name: misp-stix2
Version: 4.0.0
Summary: Produce and consume STIX 2 JSON content
Home-page: https://github.com/MISP/cti-python-stix2
License: BSD
Author: OASIS Cyber Threat Intelligence Technical Committee
Author-email: cti-users@lists.oasis-open.org
Maintainer: OASIS Cyber Threat Intelligence Technical Committee
Maintainer-email: cti-users@lists.oasis-open.org
Requires-Python: >=3.7,<4.0
Classifier: Development Status :: 5 - Production/Stable
Classifier: Intended Audience :: Developers
Classifier: License :: OSI Approved :: BSD License
Classifier: License :: Other/Proprietary License
Classifier: Programming Language :: Python :: 3
Classifier: Programming Language :: Python :: 3.7
Classifier: Programming Language :: Python :: 3.8
Classifier: Programming Language :: Python :: 3.9
Classifier: Programming Language :: Python :: 3.10
Classifier: Programming Language :: Python :: 3.11
Classifier: Programming Language :: Python :: 3.12
Classifier: Topic :: Security
Provides-Extra: semantic
Provides-Extra: taxii
Requires-Dist: haversine (>=2.6.0,<3.0.0) ; extra == "semantic"
Requires-Dist: medallion (>=3.0.0,<4.0.0) ; extra == "taxii"
Requires-Dist: pytz (>=2022.2.1,<2023.0.0)
Requires-Dist: rapidfuzz (>=2.6.0,<3.0.0) ; extra == "semantic"
Requires-Dist: requests (>=2.28.1,<3.0.0)
Requires-Dist: simplejson (>=3.17.6,<4.0.0)
Requires-Dist: stix2-patterns (>=2.0.0,<3.0.0)
Requires-Dist: taxii2-client (>=2.3.0,<3.0.0) ; extra == "taxii"
Project-URL: Bug Tracker, https://github.com/oasis-open/cti-python-stix2/issues/
Project-URL: Documentation, https://stix2.readthedocs.io/
Project-URL: Repository, https://github.com/MISP/cti-python-stix2
Project-URL: Source Code, https://github.com/oasis-open/cti-python-stix2/
